matrix_interface.py
setup.py
matrixiotyClient_v.02.egg-info/PKG-INFO
matrixiotyClient_v.02.egg-info/SOURCES.txt
matrixiotyClient_v.02.egg-info/dependency_links.txt
matrixiotyClient_v.02.egg-info/not-zip-safe
matrixiotyClient_v.02.egg-info/requires.txt
matrixiotyClient_v.02.egg-info/top_level.txt