Metadata-Version: 1.0
Name: matrixiotyClient-v.02
Version: 0.2
Summary: WIP Client package
Home-page: https://gitlab.com/chiton-corp/matrix-infrastructure
Author: matrixioty
Author-email: matrixioty@gmail.com
License: UNKNOWN
Platform: UNKNOWN
